argdump/__init__.py
argdump/_deserializer.py
argdump/_schema.py
argdump/_serializer.py
argdump/_types.py
argdump/_values.py
argdump/models.py
argdump-0.1.2.dist-info/METADATA
argdump-0.1.2.dist-info/WHEEL
argdump-0.1.2.dist-info/licenses/LICENSE
argdump-0.1.2.dist-info/RECORD
