Metadata-Version: 2.4
Name: argdump
Version: 0.1.2
Summary: Serialize and deserialize argparse parsers
Project-URL: Homepage, https://github.com/styx-api/argdump
Project-URL: Repository, https://github.com/styx-api/argdump
Project-URL: Documentation, https://niwrap.dev/argdump
Author-email: Florian Rupprecht <dair@childmind.org>
License-Expression: MIT
License-File: LICENSE
Keywords: argparse,cli,json,serialization
Classifier: Development Status :: 4 - Beta
Classifier: Intended Audience :: Developers
Classifier: License :: OSI Approved :: MIT License
Classifier: Programming Language :: Python :: 3
Classifier: Programming Language :: Python :: 3.9
Classifier: Programming Language :: Python :: 3.10
Classifier: Programming Language :: Python :: 3.11
Classifier: Programming Language :: Python :: 3.12
Classifier: Programming Language :: Python :: 3.13
Classifier: Typing :: Typed
Requires-Python: >=3.9
